Metadata-Version: 2.1
Name: django-recaptcha
Version: 3.0.0
Summary: Django recaptcha form field/widget app.
Home-page: https://github.com/torchbox/django-recaptcha
Author: Praekelt Consulting
Author-email: dev@praekelt.com
License: BSD
Project-URL: Changelog, https://github.com/torchbox/django-recaptcha/blob/main/CHANGELOG.rst
Project-URL: Issue Tracker, https://github.com/torchbox/django-recaptcha/issues
Project-URL: Discussions, https://github.com/torchbox/django-recaptcha/discussions
Keywords: django,reCAPTCHA,reCAPTCHA v2,reCAPTCHA v3
Platform: UNKNOWN
Classifier: Development Status :: 5 - Production/Stable
Classifier: Framework :: Django
Classifier: Framework :: Django :: 2.2
Classifier: Framework :: Django :: 3.2
Classifier: Framework :: Django :: 4.0
Classifier: Intended Audience :: Developers
Classifier: License :: OSI Approved :: BSD License
Classifier: Operating System :: OS Independent
Classifier: Programming Language :: Python
Classifier: Topic :: Internet :: WWW/HTTP :: Dynamic Content
Classifier: Programming Language :: Python :: 3
Classifier: Programming Language :: Python :: 3.7
Classifier: Programming Language :: Python :: 3.8
Classifier: Programming Language :: Python :: 3.9
Classifier: Programming Language :: Python :: 3.10
License-File: LICENSE
License-File: AUTHORS.rst
